CHANGELOG.md
LICENSE.txt
MANIFEST.in
README.md
requirements.txt
setup.py
django_webpack/__init__.py
django_webpack/compiler.py
django_webpack/exceptions.py
django_webpack/models.py
django_webpack/settings.py
django_webpack/staticfiles.py
django_webpack.egg-info/PKG-INFO
django_webpack.egg-info/SOURCES.txt
django_webpack.egg-info/dependency_links.txt
django_webpack.egg-info/requires.txt
django_webpack.egg-info/top_level.txt
django_webpack/services/__init__.py
django_webpack/services/package.json
django_webpack/services/webpack.js