Metadata-Version: 1.0
Name: django-webpack
Version: 3.1.1
Summary: Generate Webpack bundles from a Django application.
Home-page: https://github.com/markfinger/django-webpack
Author: Mark Finger
Author-email: markfinger@gmail.com
License: UNKNOWN
Platform: UNKNOWN
